<?xml version="1.0" encoding="UTF-8"?>
<objects serializationModel="Studio.02.02.00">
	<object class="AudioFile" id="{e80bc6a6-4242-4083-adfb-7d1b0dad2500}">
		<property name="assetPath">
			<value>Click_Electronic_13.mp3</value>
		</property>
		<property name="frequencyInKHz">
			<value>44.0999985</value>
		</property>
		<property name="channelCount">
			<value>2</value>
		</property>
		<property name="length">
			<value>0.31346938775510202</value>
		</property>
		<relationship name="masterAssetFolder">
			<destination>{6201eb9a-7f1f-42b9-afa5-e5cd68f81784}</destination>
		</relationship>
	</object>
</objects>
